PyOptDE/__init__.py
PyOptDE/algorithm/PyOptDE.py
PyOptDE/algorithm/__init__.py
PyOptDE/algorithm/func_wrapper.py
PyOptDE/algorithm/multiple_differential_evolution.py
PyOptDE/algorithm/single_differential_evolution.py
PyOptDE/algorithm/utils.py
PyOptDE/examples/__init__.py
PyOptDE/examples/full_toy.py
PyOptDE/examples/simple_toy.py
PyOptDE-1.1.1.dist-info/LICENSE
PyOptDE-1.1.1.dist-info/METADATA
PyOptDE-1.1.1.dist-info/WHEEL
PyOptDE-1.1.1.dist-info/top_level.txt
PyOptDE-1.1.1.dist-info/RECORD
