Metadata-Version: 2.1
Name: PyOptDE
Version: 1.1.1
Summary: An implementation of the Differential Evolution algorithm.
Home-page: https://github.com/lucasresenderc/PyOptDE
Author: Lucas Resende
Author-email: lucasresenderc@gmail.com
License: UNKNOWN
Platform: UNKNOWN
Classifier: Programming Language :: Python :: 3
Classifier: License :: OSI Approved :: GNU General Public License v3 (GPLv3)
Classifier: Operating System :: OS Independent
Requires-Python: >=3.6
Requires-Dist: numpy
Requires-Dist: matplotlib
Requires-Dist: scipy
